aio_nacos/__init__.py
aio_nacos/aio_nacos.py
aio_nacos/nacos_config.py
aio_nacos/nacos_error.py
aio_nacos/nacos_models.py
aio_nacos/nacos_services.py
aio_nacos-0.1.5.dist-info/LICENSE
aio_nacos-0.1.5.dist-info/METADATA
aio_nacos-0.1.5.dist-info/WHEEL
aio_nacos-0.1.5.dist-info/top_level.txt
aio_nacos-0.1.5.dist-info/RECORD
